{















        "entries": [
          {
            "stringId": "1954563637975752704",
            "femaleVariant": "生活有时候真是美好！"
          },
          {
            "stringId": "1954563637992529924",
            "femaleVariant": "我要不要再去买一手？"
          },
          {
            "stringId": "1954563638042861572",
            "femaleVariant": "这么粗鲁干嘛！"
          },
          {
            "stringId": "1954563638059638788",
            "femaleVariant": "小心看路！"
          },
          {
            "stringId": "1954563638093193220",
            "femaleVariant": "我跟你说什么来着？"
          },
          {
            "stringId": "1954563638143524868",
            "femaleVariant": "你是什么意思，什么…？我赢了…！你这辈子都没见过那么多钱…啊，对呀…！我真是太走运了！"
          },
          {
            "stringId": "1954563638160302084",
            "femaleVariant": "十年了，终于看到回报了…！命运啊！这是第一次…！我也不敢相信。"
          },
          {
            "stringId": "1954563638193856516",
            "femaleVariant": "来吧。我请客！"
          },
          {
            "stringId": "1954563638344851460",
            "femaleVariant": "救命啊！"
          },
          {
            "stringId": "1954563638378405892",
            "femaleVariant": "呼呼…她还在追我吗？！",
            "maleVariant": "他还在追我吗？！"
          },
          {
            "stringId": "1954563638445514756",
            "femaleVariant": "我给你钱！我有钱！"
          },
          {
            "stringId": "1954563638462291972",
            "femaleVariant": "我的人生才刚开始！"
          },
          {
            "stringId": "1954563638546178052",
            "femaleVariant": "我不需要人陪。我自己就够了。"
          },
          {
            "stringId": "1954563638562955268",
            "femaleVariant": "你怎么还不走开啊？"
          }
        ]
      }



