{















        "entries": [
          {
            "stringId": "2162125980397449216",
            "femaleVariant": "你就不能闭嘴听别人说话吗！"
          },
          {
            "stringId": "2213044531687165952",
            "femaleVariant": "不，你才闭嘴！你知道个屁，老不死的。他们害死多少人了？！"
          },
          {
            "stringId": "2218748144354955264",
            "femaleVariant": "不如说是救了多少人，你个窝囊废！这才是真相！"
          },
          {
            "stringId": "2218748662183727104",
            "femaleVariant": "好啊，有真相你说啊。我们听听看啊！"
          },
          {
            "stringId": "2218748980833390592",
            "femaleVariant": "讲就讲，不知死活的小子！要不是瓦伦蒂诺，你每天只能抱着平板躲在屋里！是他们扫清了街头！"
          },
          {
            "stringId": "2218749428583731200",
            "femaleVariant": "放你娘的屁！以前警察管的不好吗？我们还不用交钱！这才是正道！"
          },
          {
            "stringId": "2218759142944116736",
            "femaleVariant": "妈呀。警察？！他们根本不来这儿！这里跟战场有什么两样？但瓦伦蒂诺来了，他们维持秩序。这就是真相。"
          },
          {
            "stringId": "2218760070136958976",
            "femaleVariant": "真什么相，你跟你那瓦什么帮去死吧！"
          }
        ]
      }



