{















        "entries": [
          {
            "stringId": "1851824651336962048",
            "femaleVariant": "已检测到新的指纹。"
          },
          {
            "stringId": "1851825516974198784",
            "femaleVariant": "搞毛？"
          },
          {
            "stringId": "1851830037846708224",
            "femaleVariant": "音量提高 33%。已检测到新的指纹！"
          },
          {
            "stringId": "1851830744771481600",
            "femaleVariant": "那是你主人吗？"
          },
          {
            "stringId": "1851831074527662080",
            "femaleVariant": "四季宝？你真叫这个？"
          },
          {
            "stringId": "1851833347102232576",
            "femaleVariant": "垃圾堆里那货，是你主人？"
          },
          {
            "stringId": "1851833417868529664",
            "femaleVariant": "呵，四季宝？真叫这个？"
          },
          {
            "stringId": "1851834306507329536",
            "femaleVariant": "检查内存中…可用资源—100%。所有文件均已手动删除。"
          },
          {
            "stringId": "1851835534045892608",
            "femaleVariant": "音量提高 66%，名称——"
          },
          {
            "stringId": "1851836528733474816",
            "femaleVariant": "你…你是个什么鬼东西？"
          },
          {
            "stringId": "1851836695817768960",
            "femaleVariant": "用户询问。技术规格：HJKE-11 内置 AI 智能手枪。试验型号。"
          },
          {
            "stringId": "1851837536373067776",
            "femaleVariant": "可能原因：盗窃。原所有者——数据缺失。"
          },
          {
            "stringId": "1851838599696240640",
            "femaleVariant": "建议的解决方案：无。"
          },
          {
            "stringId": "1851855476971556868",
            "femaleVariant": "你没坏吧？"
          },
          {
            "stringId": "1851856505767219200",
            "femaleVariant": "你有什么用？"
          },
          {
            "stringId": "1851856753247932416",
            "femaleVariant": "我能给你换个名字吗？"
          },
          {
            "stringId": "1851878642884300800",
            "femaleVariant": "能给你换个名字吗？"
          },
          {
            "stringId": "1851881179716800512",
            "femaleVariant": "不能。"
          },
          {
            "stringId": "1851882733287002112",
            "femaleVariant": "为什么？我不是你的新主人吗…"
          },
          {
            "stringId": "1851883329364709376",
            "femaleVariant": "音量提高 300%。不能！"
          },
          {
            "stringId": "1851884493703499776",
            "femaleVariant": "你的功能都还正常吧？"
          },
          {
            "stringId": "1851885352428523520",
            "femaleVariant": "正在运行系统诊断。检测时间需要大约 47 秒。"
          },
          {
            "stringId": "1851891699417108480",
            "femaleVariant": "好吧，那你有什么用？除了冲我耳朵吵吵以外。"
          },
          {
            "stringId": "1851907166064103424",
            "femaleVariant": "主要功能：自动瞄准。当用户遇到严重威胁时，具备自动开枪能力。"
          },
          {
            "stringId": "1851907738955698180",
            "femaleVariant": "请选冷血杀手。"
          },
          {
            "stringId": "1851907975078236160",
            "femaleVariant": "爱汪星人的和平人士，听起来好点。"
          },
          {
            "stringId": "1851908611823915008",
            "femaleVariant": "“冷血杀手。”我就喜欢这种枪。"
          },
          {
            "stringId": "1851909335374909440",
            "femaleVariant": "正在调整设置…"
          },
          {
            "stringId": "1851909589130301440",
            "femaleVariant": "呃，我还是选“爱狗的和平人士”吧…"
          },
          {
            "stringId": "1853436028560363520",
            "femaleVariant": "请从以下两种操作模式中进行选择。第一种模式，爱狗的和平人士。该模式会瞄准敌人的下肢。"
          },
          {
            "stringId": "1864759790736297984",
            "femaleVariant": "名称。四季宝。"
          },
          {
            "stringId": "1864774847314579456",
            "femaleVariant": "我又不聋！"
          },
          {
            "stringId": "1864775203394211840",
            "femaleVariant": "明白。听力指标正常。可能的问题：智商过低。语速降低 33%。我，的，名，称，是，四季宝。"
          },
          {
            "stringId": "1864776540504772608",
            "femaleVariant": "不，我只是…呃。算了。"
          },
          {
            "stringId": "1864782527924064256",
            "femaleVariant": "我有一个，你归我了。"
          },
          {
            "stringId": "1864783066556583936",
            "femaleVariant": "正在处理请求…未发现反对项。"
          },
          {
            "stringId": "1864786060970872832",
            "femaleVariant": "需要提供管理员权限才能完成该操作。你没有所需的权限。"
          },
          {
            "stringId": "1864788820604801024",
            "femaleVariant": "梆梆哔铛，梆梆哔铛梆…"
          },
          {
            "stringId": "1864792187473285120",
            "femaleVariant": "你…你在干嘛？"
          },
          {
            "stringId": "1864793857678692352",
            "femaleVariant": "我在通过轻松的曲调舒缓无聊的等待时间。"
          },
          {
            "stringId": "1864794534672912384",
            "femaleVariant": "梆梆哔铛，梆梆哔铛梆…"
          },
          {
            "stringId": "1864795319980838912",
            "femaleVariant": "检测已成功完成。程序：“四季宝 v0.01 ALPHA”，目前运行正常。"
          },
          {
            "stringId": "1864810409308246016",
            "femaleVariant": "第二种模式，冷血杀手。该模式仅会瞄准敌人的头部。"
          },
          {
            "stringId": "1864815046883069952",
            "femaleVariant": "呃…"
          },
          {
            "stringId": "1864815275573301248",
            "femaleVariant": "已选择模式 - 冷血杀手。祝你屠杀愉快！"
          },
          {
            "stringId": "1864817097981612032",
            "femaleVariant": "梆梆哔铛，梆梆哔铛啊…"
          },
          {
            "stringId": "1864821409893896192",
            "femaleVariant": "已选择模式 - 爱狗的和平人士。请尽情对敌人造成终身残疾！"
          }
        ]
      }



