{















        "entries": [
          {
            "stringId": "1777673526209060864",
            "femaleVariant": "你看，大家都是干黑客的…"
          },
          {
            "stringId": "1777673849103360004",
            "femaleVariant": "你能教我几手吗？"
          },
          {
            "stringId": "1777674139936399360",
            "femaleVariant": "我在哪儿见过你…"
          },
          {
            "stringId": "1777675953134018564",
            "femaleVariant": "我…我以前在哪儿见过你…"
          },
          {
            "stringId": "1777675953134018572",
            "femaleVariant": "抱歉，你肯定是认错人了。"
          },
          {
            "stringId": "1941427920394907648",
            "femaleVariant": "和罗格合作是什么样的？"
          },
          {
            "stringId": "1941429259451625472",
            "femaleVariant": "有没有什么行家的窍门儿？"
          },
          {
            "stringId": "1941431684312985600",
            "femaleVariant": "那必须有啊。罗格看得上你，那肯定有她的道理。"
          },
          {
            "stringId": "1941432754581925888",
            "femaleVariant": "我可以教你几招巴特莫斯时代的绝活儿。"
          },
          {
            "stringId": "1941433570608934912",
            "femaleVariant": "拉奇·巴特莫斯？传说中的巴特莫斯？你不是在耍我吧？"
          },
          {
            "stringId": "1941435270073806848",
            "femaleVariant": "彻底消失之前，他在深网最黑暗的角落里发布了一大批破解入侵对抗电元的程序和原型。"
          },
          {
            "stringId": "1941438056182181888",
            "femaleVariant": "我听说过这人有多偏执。知道他最后怎么了吗？"
          },
          {
            "stringId": "1941438867645788160",
            "femaleVariant": "哼，谁知道呢。不过我还真挖出了几个经典的巴特莫斯宝藏。来，我演示给你看。"
          },
          {
            "stringId": "1941440636333453312",
            "femaleVariant": "给罗格干活儿，是什么感觉？"
          },
          {
            "stringId": "1941442575007870976",
            "femaleVariant": "等等…新闻54台和荒坂的谈判，我想起来了…就那次安防部的赛博疯子丑闻。"
          },
          {
            "stringId": "1941445151837253632",
            "femaleVariant": "你以前是给荒坂工作的。那次泄露也是你干的，对不对？哈哈，我以为你死了。可眼下你人就在来生！"
          },
          {
            "stringId": "1941446732200669184",
            "femaleVariant": "没想到你也是穿西装的。我怀念的，只有那里的新鲜空气。"
          },
          {
            "stringId": "1941449279518928896",
            "femaleVariant": "还行吧。"
          },
          {
            "stringId": "1941456656360140800",
            "femaleVariant": "就这样？“还行吧？”"
          },
          {
            "stringId": "1941456983029313536",
            "femaleVariant": "如果你想听罗格的事情，自己去问她。她肯定乐意告诉你。"
          },
          {
            "stringId": "2534350856845660160",
            "femaleVariant": "我们回头再说。"
          }
        ]
      }



