{















        "entries": [
          {
            "stringId": "1338559622542442496",
            "femaleVariant": "再跟我讲讲兰迪。他是个什么样的孩子？"
          },
          {
            "stringId": "1396774671519178752",
            "femaleVariant": "小偷小摸、吸毒嗑药、离家出走，就这种。"
          },
          {
            "stringId": "1401040175171756032",
            "femaleVariant": "OK，那你说吧…"
          },
          {
            "stringId": "1401042845500563456",
            "femaleVariant": "你再跟我说说兰迪的事？"
          },
          {
            "stringId": "1401045522640920576",
            "femaleVariant": "兰迪的爸爸是谁？"
          },
          {
            "stringId": "1401046087731109888",
            "femaleVariant": "兰迪，他爸爸呢？"
          },
          {
            "stringId": "1401053490375680000",
            "femaleVariant": "有个警察舅舅也敢这么混蛋…"
          },
          {
            "stringId": "1401053747838836736",
            "femaleVariant": "有些人生下来就擅长找麻烦。比如说兰迪。"
          },
          {
            "stringId": "1401057441661706240",
            "femaleVariant": "几年前就翘了。黑帮火并。"
          },
          {
            "stringId": "1537312397961904128",
            "femaleVariant": "我只是…很难开口跟别人说，尤其是糟心事。"
          },
          {
            "stringId": "1780929152491163648",
            "femaleVariant": "你就不怕雅文出卖你，跑去跟她上司告黑状吗？"
          },
          {
            "stringId": "1780930867542069248",
            "femaleVariant": "你觉得这么一来，雅文她还会愿意帮我们吗？",
            "maleVariant": "你觉得这么一来，雅文她还会帮我们吗？"
          },
          {
            "stringId": "1780931966516826112",
            "femaleVariant": "那说好了——找到兰迪之后，我们就去喝他个昏天黑地。"
          },
          {
            "stringId": "1780932008661192704",
            "femaleVariant": "眼下咱们还是集中精神找兰迪吧。"
          },
          {
            "stringId": "1780932115615944708",
            "femaleVariant": "还是集中精力找兰迪吧。"
          },
          {
            "stringId": "1780932497180168192",
            "femaleVariant": "我可记下了，下次喝酒。"
          },
          {
            "stringId": "1782223670917337088",
            "femaleVariant": "我们难道不应该去哈里斯的住处吗？"
          },
          {
            "stringId": "1782262268496580608",
            "femaleVariant": "有其父必有其子。"
          },
          {
            "stringId": "1782383506447536132",
            "femaleVariant": "我很好奇，干吗不去哈里斯的公寓找？"
          },
          {
            "stringId": "1782383506447536144",
            "femaleVariant": "再说了，我们也只是碰运气，看能不能在兰迪家里找到哈里斯的眉目。"
          },
          {
            "stringId": "1782383506447536156",
            "femaleVariant": "听上去很勉强。"
          },
          {
            "stringId": "1782383506464313344",
            "femaleVariant": "不然现在也没别的办法。"
          },
          {
            "stringId": "1782394969077714944",
            "femaleVariant": "被踢出了警队…"
          },
          {
            "stringId": "1782400463632732160",
            "femaleVariant": "你难道是被开除的？"
          },
          {
            "stringId": "1782487452558168064",
            "femaleVariant": "丢了警徽，还瞒着我——为什么？"
          },
          {
            "stringId": "1782487534045106180",
            "femaleVariant": "闹了半天，你是被踢出去的啊…"
          },
          {
            "stringId": "1782489968704360448",
            "femaleVariant": "呃，是停职。市长死得明显有问题，调查结果又不让公布…我跟局里吵了一架。"
          },
          {
            "stringId": "1782490296598269952",
            "femaleVariant": "不用问，能猜到你当时什么心情。"
          },
          {
            "stringId": "1782491664813789184",
            "femaleVariant": "别提了。"
          },
          {
            "stringId": "1782493206992261120",
            "femaleVariant": "不知道。"
          },
          {
            "stringId": "1782493312353177600",
            "femaleVariant": "你这样可不地道啊。"
          },
          {
            "stringId": "1783402570485731328",
            "femaleVariant": "我们毕竟是朋友，她应该不会。"
          },
          {
            "stringId": "1783446037299597312",
            "femaleVariant": "嗯。吵归吵，我们最后总能和好的…"
          },
          {
            "stringId": "1783447658247098368",
            "femaleVariant": "下次喝酒的时候再跟你说。"
          },
          {
            "stringId": "1783452580413837312",
            "femaleVariant": "当然了。"
          },
          {
            "stringId": "1783458130853761024",
            "femaleVariant": "乐意奉陪。"
          },
          {
            "stringId": "1815737714720186368",
            "femaleVariant": "剩下乔斯和三个孩子，哼，不过她是个坚强的母亲。"
          },
          {
            "stringId": "1841609618746380288",
            "femaleVariant": "雅文会帮助我们吗？"
          },
          {
            "stringId": "1841609835138912256",
            "femaleVariant": "雅文不会出卖你吧？"
          },
          {
            "stringId": "1908178454259982336",
            "femaleVariant": "那儿是个独栋。我认为他不会把绑架来的人藏在地下室里。"
          },
          {
            "stringId": "1908216662825918464",
            "femaleVariant": "呃……没错。"
          },
          {
            "stringId": "1908263265267900416",
            "femaleVariant": "话说回来，要是不得已跟她真闹翻了，不用怕，我手里也不是没有她的把柄…"
          },
          {
            "stringId": "1912776659653758976",
            "femaleVariant": "好，就是这儿了。"
          },
          {
            "stringId": "1925708937564393472",
            "femaleVariant": "那好吧。至少你可以告诉我这是要去哪儿。"
          },
          {
            "stringId": "1925710024610549760",
            "femaleVariant": "去乔斯家。"
          },
          {
            "stringId": "1925710242194264064",
            "femaleVariant": "兰迪妈妈那儿。"
          },
          {
            "stringId": "1925710454023393280",
            "femaleVariant": "她以为兰迪只是离家出走了。记住，先别提绑架的事。"
          }
        ]
      }



