{















        "entries": [
          {
            "stringId": "1933089478186401796",
            "femaleVariant": "嘿，最近好不好？"
          },
          {
            "stringId": "1933089478219956228",
            "femaleVariant": "你有事儿吗？"
          },
          {
            "stringId": "1933089478320619520",
            "femaleVariant": "等一下，我们还没说完。"
          },
          {
            "stringId": "1933089478337396740",
            "femaleVariant": "等等，还没完呢。"
          },
          {
            "stringId": "1933089478421282816",
            "femaleVariant": "嗯…我们继续讨论。"
          },
          {
            "stringId": "1933089478438060036",
            "femaleVariant": "正如刚才所说…"
          },
          {
            "stringId": "1933089478471614464",
            "femaleVariant": "快啊，有话就说。"
          },
          {
            "stringId": "1933089478488391684",
            "femaleVariant": "V，我等着呢。"
          },
          {
            "stringId": "1933089478723272708",
            "femaleVariant": "别挡道。"
          },
          {
            "stringId": "1933089478740049924",
            "femaleVariant": "诶！"
          },
          {
            "stringId": "1933089729492320260",
            "femaleVariant": "有个工作，需要去抓个人。"
          },
          {
            "stringId": "1933089729509097476",
            "femaleVariant": "目标我告诉你。至于怎么行动，随你。"
          },
          {
            "stringId": "1933089729760755716",
            "femaleVariant": "有人需要帮忙，咱们就得出面。"
          },
          {
            "stringId": "1933089729777532932",
            "femaleVariant": "我不会忘本，特别是他们遇到麻烦的时候。"
          },
          {
            "stringId": "1933089729811087364",
            "femaleVariant": "搞破坏。我的专长。"
          },
          {
            "stringId": "1933089729827864580",
            "femaleVariant": "我客户想找人去挑事儿。钱你不用担心。"
          },
          {
            "stringId": "1933089729861419012",
            "femaleVariant": "任务很简单，跑线，从A点送到B点。"
          },
          {
            "stringId": "1933089729878196228",
            "femaleVariant": "我需要个靠得住的人带货。比如说你。"
          },
          {
            "stringId": "1933089729911750660",
            "femaleVariant": "客户需要个东西，但它在别人手上。"
          },
          {
            "stringId": "1933089729945305092",
            "femaleVariant": "我的客户想要某样东西。你去弄来。"
          },
          {
            "stringId": "1933089729962082308",
            "femaleVariant": "去帮我顺个东西吧。动静是大是小我无所谓。"
          },
          {
            "stringId": "1933089729995636740",
            "femaleVariant": "你去帮我弄个东西。问题是，要从别人的手里抢。"
          },
          {
            "stringId": "1950443769129631744",
            "femaleVariant": "把东西放储物柜里，其它的我来处理。"
          },
          {
            "stringId": "1950443833117933568",
            "femaleVariant": "把货留在柜子里，其余的你就不用管了。"
          }
        ]
      }



