{















        "entries": [
          {
            "stringId": "1882226030505508864",
            "femaleVariant": "我能看看你的东西吗？"
          },
          {
            "stringId": "1882226030505508880",
            "femaleVariant": "这附近好多虎爪帮的人。"
          },
          {
            "stringId": "1882226031327592452",
            "femaleVariant": "能看看你的东西吗？"
          },
          {
            "stringId": "1882226031377924100",
            "femaleVariant": "当然！我肯定你能找到喜欢的。"
          },
          {
            "stringId": "1882226031428255748",
            "femaleVariant": "这地方真热闹。虎爪帮的人尤其多。"
          },
          {
            "stringId": "1882226031445032964",
            "femaleVariant": "都是来自各行各业的人。"
          },
          {
            "stringId": "1912580973309251584",
            "femaleVariant": "嗯哼。对他们挺了解的？"
          },
          {
            "stringId": "1912581215572250624",
            "femaleVariant": "他们不喜欢人瞎打听。"
          }
        ]
      }



