{















        "entries": [
          {
            "stringId": "1935671434919981056",
            "femaleVariant": "What're you selling?"
          },
          {
            "stringId": "1935671434919981072",
            "femaleVariant": "You got anything... unconventional?"
          },
          {
            "stringId": "1935671434987089924",
            "femaleVariant": "What're you carryin'?"
          },
          {
            "stringId": "1935671434987089932",
            "femaleVariant": "Firearms. Best in all the Badlands."
          },
          {
            "stringId": "1935671435020644356",
            "femaleVariant": "Now that I think about it, you don't have NCPD bothering you way out here. No corpo supply inspections either..."
          },
          {
            "stringId": "1935671435020644364",
            "femaleVariant": "I'm sure we can find you something."
          },
          {
            "stringId": "1975106424220733440",
            "femaleVariant": "You got anything... unconventional? That I wouldn't find in the city?"
          }
        ]
      }



