{















        "entries": [
          {
            "stringId": "1963273693441335296",
            "femaleVariant": "That attack... in Paris... that was us?"
          },
          {
            "stringId": "1966148764259041280",
            "femaleVariant": "Keep it down, will ya? That's classified."
          },
          {
            "stringId": "1966149007847440384",
            "femaleVariant": "I didn't sign up for this, man. Someone's gonna find out."
          },
          {
            "stringId": "1966149272273141760",
            "femaleVariant": "Whoever needs to know already knows. We keep our mouths shut, OK?"
          },
          {
            "stringId": "1966149792333283328",
            "femaleVariant": "What did you think that extra seven per cent of the budget was for?"
          },
          {
            "stringId": "1966149978661044224",
            "femaleVariant": "If this gets out, no fucking seven per cent's gonna save our asses!"
          },
          {
            "stringId": "1966150236073869312",
            "femaleVariant": "How do you think it'll look? Supplying weapons for riots that our people started?"
          },
          {
            "stringId": "1966150663825768448",
            "femaleVariant": "\"Militech denies any involvement or wrongdoing.\""
          }
        ]
      }



