{















        "entries": [
          {
            "stringId": "2161911343972904960",
            "femaleVariant": "<kiroshi l=\"mex\" o=\"Sí, pues hoy ya no tenemos, ¿sabes? Se nos acabó, ¿bueno?\" t=\"Yeah well, we don't got it today, y'know? All out, yeah?\" b=\"\" a=\"\"/>"
          },
          {
            "stringId": "2223061329442607104",
            "femaleVariant": "Mhm. Right, OK."
          },
          {
            "stringId": "2223061481091862528",
            "femaleVariant": "<kiroshi l=\"mex\" o=\"Sí, pues los Calle 6 le dispararon a la camioneta del reparto o algo así. ¿Vas a pedir algo?\" t=\"Yeah, 6th Street, like, shot up the delivery van or somethin'. You gettin' anything?\" b=\"\" a=\"\"/>"
          },
          {
            "stringId": "2223075623899074560",
            "femaleVariant": "Delivery? You mean Hector's van? He OK?"
          },
          {
            "stringId": "2227506765817548800",
            "femaleVariant": "<kiroshi l=\"mex\" o=\"¿Cómo voy a saberlo? Soy nueva, ¿sí? Solo sé que le dispararon.\" t=\"Like I know? I'm new, right? All's I know is they shot it.\" b=\"\" a=\"\"/>"
          }
        ]
      }



