{















        "entries": [
          {
            "stringId": "1694200870079320064",
            "femaleVariant": "Don't like this, not one bit."
          },
          {
            "stringId": "1694201234463674368",
            "femaleVariant": "One-Fourteen to command, is this a test?"
          },
          {
            "stringId": "1694201299374723072",
            "femaleVariant": "Fuck a muffin – gonna have to stay late again."
          },
          {
            "stringId": "1694201482246377472",
            "femaleVariant": "Lockdown deactivated."
          },
          {
            "stringId": "1694241712013856768",
            "femaleVariant": "Code red initiated."
          },
          {
            "stringId": "1733107627241263104",
            "femaleVariant": "Ya thinkin' it's serious?"
          },
          {
            "stringId": "1733110306948534272",
            "femaleVariant": "Didn't you hear? Everyone is to stay in position."
          },
          {
            "stringId": "1733110568404668416",
            "femaleVariant": "What happened? Shouldn't we go back up to the surface?"
          },
          {
            "stringId": "1733110975386374144",
            "femaleVariant": "No need for concern."
          },
          {
            "stringId": "1733111246002868224",
            "femaleVariant": "Code red is no need for concern?"
          },
          {
            "stringId": "1733117279425286144",
            "femaleVariant": "And? How about now?"
          },
          {
            "stringId": "1733117279425286152",
            "femaleVariant": "Yes, you can pass through to the other side of the building."
          },
          {
            "stringId": "1733122061904924672",
            "femaleVariant": "Seriously? I thought this was some kinda test."
          },
          {
            "stringId": "1733132990348546048",
            "femaleVariant": "Screw this. I'm done with it."
          },
          {
            "stringId": "1802383447884091392",
            "femaleVariant": "Does anyone know what happened?"
          },
          {
            "stringId": "1802390543757266944",
            "femaleVariant": "Sure sounds it. We'll be here till sundown at least."
          },
          {
            "stringId": "1802390653396373504",
            "femaleVariant": "It always like this around here?"
          },
          {
            "stringId": "1802397824213372928",
            "femaleVariant": "Affirmative. I'll keep my eyes wide open."
          },
          {
            "stringId": "1802397919491182592",
            "femaleVariant": "One-Fourteen – over and out."
          },
          {
            "stringId": "1802400634699042816",
            "femaleVariant": "Paul is going to kill me."
          },
          {
            "stringId": "1802400717930811392",
            "femaleVariant": "This is the third time we'll be rescheduling this anniversary."
          },
          {
            "stringId": "1802406708202229760",
            "femaleVariant": "All employees are to remain where they are until the lockdown has been lifted."
          },
          {
            "stringId": "1802408236271063040",
            "femaleVariant": "All employees are kindly requested to please resume their duties."
          },
          {
            "stringId": "1802421927821496320",
            "femaleVariant": "Kang Tao's offer – I'm going to take it."
          },
          {
            "stringId": "1802421995769221120",
            "femaleVariant": "You might at least get a window in your office over there."
          },
          {
            "stringId": "1819753106941726720",
            "femaleVariant": "Nah, almost never. That's why I don't like it one bit."
          },
          {
            "stringId": "1831352666851954688",
            "femaleVariant": "I am to escort you there."
          },
          {
            "stringId": "1831352732383760384",
            "femaleVariant": "You did not answer my question."
          }
        ]
      }



