{















        "entries": [
          {
            "stringId": "1814003168238804992",
            "femaleVariant": "Gah, fuck!"
          },
          {
            "stringId": "1814003554198659076",
            "femaleVariant": "What a performance, huh? Know what it was about?"
          },
          {
            "stringId": "1814003838220148736",
            "femaleVariant": "Jesus... the fuck do you want from me?"
          },
          {
            "stringId": "1814006118914891776",
            "femaleVariant": "It's all goin' too slow."
          },
          {
            "stringId": "1814222139227545600",
            "femaleVariant": "You don't care if I live."
          },
          {
            "stringId": "1814225625163931648",
            "femaleVariant": "Still don't see how Mikoshi's linked to my chip problem."
          },
          {
            "stringId": "1814226536384864256",
            "femaleVariant": "Not the brightest bulb on stage, are ya?"
          },
          {
            "stringId": "1814226885552283652",
            "femaleVariant": "What do Soulkiller and Mikoshi have to do with me?"
          },
          {
            "stringId": "1863683300736393216",
            "femaleVariant": "Leave me alone."
          },
          {
            "stringId": "1863685585373782016",
            "femaleVariant": "Wanted me dead, said so yourself."
          },
          {
            "stringId": "1863686203597414400",
            "femaleVariant": "Made it pretty clear since that I changed my mind. Want you to live now."
          },
          {
            "stringId": "1863686776958771200",
            "femaleVariant": "Asked you already... what the hell ya want from me?"
          },
          {
            "stringId": "1863691067094228992",
            "femaleVariant": "See, me and Arasaka, we got a half-century-old score needs settling, and I plan to do it."
          },
          {
            "stringId": "1863695602713911300",
            "femaleVariant": "Gonna make a terrorist of me?"
          },
          {
            "stringId": "1863698666250330112",
            "femaleVariant": "Funny guy."
          },
          {
            "stringId": "1863698945456758784",
            "femaleVariant": "Never been recruited into a terrorist cell before. Feel kinda honored, actually."
          },
          {
            "stringId": "1863703184203603968",
            "femaleVariant": "Listen, I know things, where we can save your life, who can help us do that."
          },
          {
            "stringId": "1863704887040696320",
            "femaleVariant": "You'll get rid of the chip, I'll smash 'Saka – win-win, kid."
          },
          {
            "stringId": "1863707995489722368",
            "femaleVariant": "It's honestly as if you were tryin' to make exactly no sense."
          },
          {
            "stringId": "1863710163122806784",
            "femaleVariant": "Soulkiller's what we need and Mikoshi's how we grab it."
          },
          {
            "stringId": "1863716674343559172",
            "femaleVariant": "Mikoshi – what's that, exactly?"
          },
          {
            "stringId": "1863716875905032192",
            "femaleVariant": "But I don't trust you."
          },
          {
            "stringId": "1863718324919623680",
            "femaleVariant": "You're just a hallucination."
          },
          {
            "stringId": "1863720343487143936",
            "femaleVariant": "You know you're just an irritating hallucination, right? Should just ignore you."
          },
          {
            "stringId": "1863720796941737984",
            "femaleVariant": "And you're a walkin' corpse. Should just wait till your mind shrivels to nothing and frees up space for me."
          },
          {
            "stringId": "1863723631167168512",
            "femaleVariant": "OK, so, this Mikoshi – what is it, exactly?"
          },
          {
            "stringId": "1863724911453298688",
            "femaleVariant": "Don't trust you – clear, right? So why would I trust in your plan?"
          },
          {
            "stringId": "1863726168351989760",
            "femaleVariant": "'Cause you've heard your death knell but you'd rather live."
          },
          {
            "stringId": "1863729497740173312",
            "femaleVariant": "So if you're done bitchin', I'd be happy to explain – sound good?"
          },
          {
            "stringId": "1863736361148243972",
            "femaleVariant": "Mikoshi – what's that, exactly?"
          },
          {
            "stringId": "1863736773951643648",
            "femaleVariant": "Not particularly."
          },
          {
            "stringId": "1863737072586088448",
            "femaleVariant": "Not really, no."
          },
          {
            "stringId": "1864880346440949760",
            "femaleVariant": "I got a get-outta-jail-free card. I'd be a fuckin' fool not to take advantage."
          },
          {
            "stringId": "1864886551561396224",
            "femaleVariant": "OK, basics. If you're jacked in, cruisin' the Net, Arasaka can use Soulkiller, an AI, to trap, fry and pack away your psyche, your mind and your soul."
          },
          {
            "stringId": "1864888403229171712",
            "femaleVariant": "Followin' so far?"
          },
          {
            "stringId": "1864889590535970816",
            "femaleVariant": "Yeah, seen the memories – did a real number on ya."
          },
          {
            "stringId": "1864889878282002432",
            "femaleVariant": "OK... Seems we got a few more things to broach than I thought, but that'll come later."
          },
          {
            "stringId": "1864890691641434112",
            "femaleVariant": "Anyway, when Soulkiller fries, roasts and boils you, you die. But the contents of your mind get copied to an engram first."
          },
          {
            "stringId": "1864892098796871680",
            "femaleVariant": "Sure. That's how you became a construct."
          },
          {
            "stringId": "1864898411023065088",
            "femaleVariant": "Exactly. Now, Mikoshi's the place Soulkiller operates out of, where it stores its victims' engrams."
          },
          {
            "stringId": "1864899650993545220",
            "femaleVariant": "Me and Mikoshi – how're we linked at all?"
          },
          {
            "stringId": "1864899843696648192",
            "femaleVariant": "Cut to the chase."
          },
          {
            "stringId": "1864899994741923840",
            "femaleVariant": "C'mon, c'mon – you got more to say, so just say it."
          },
          {
            "stringId": "1864905855325462528",
            "femaleVariant": "And, uh, how you plan to smash Arasaka this time? Got another nuke tucked away?"
          },
          {
            "stringId": "1864911452187942912",
            "femaleVariant": "Fifty years back, ops on the human mind – Mikoshi was the sole place on Earth where they did anything like that."
          },
          {
            "stringId": "1864936543554658304",
            "femaleVariant": "Bet it still is today. Tellin' ya, all roads lead there. It's where we'll settle our biz – you yours, me mine."
          },
          {
            "stringId": "1866211050235912192",
            "femaleVariant": "Leave me alone.",
            "maleVariant": "Lemme alone."
          },
          {
            "stringId": "1866216751385567232",
            "femaleVariant": "Can't find the words to describe exactly how fucked up you are."
          },
          {
            "stringId": "1866224779165982720",
            "femaleVariant": "I just needed a calmer moment to think. And yeah, figured since fate gave me another shot, I'll take it."
          },
          {
            "stringId": "1866226424138457088",
            "femaleVariant": "To live life to the fullest? See the northern lights, run with the mechbulls or with gazelles on a safari?"
          },
          {
            "stringId": "1866227557489729536",
            "femaleVariant": "To finish what I started. I'm back in the game. Want 'Saka out, so I'm gonna need you in."
          },
          {
            "stringId": "1866228843245232128",
            "femaleVariant": "Might even laugh if it didn't hurt so much."
          },
          {
            "stringId": "1866308089368043524",
            "femaleVariant": "Arasaka – how you plan to destroy it this time?"
          },
          {
            "stringId": "1866422988131819520",
            "femaleVariant": "Distracting you. That was Hanako Arasaka, attemptin' to--"
          },
          {
            "stringId": "1866429772317876224",
            "femaleVariant": "W-what's goin' on?"
          },
          {
            "stringId": "1866445261865771008",
            "femaleVariant": "So, you found Hellman and got what to show for it? Empty promises."
          },
          {
            "stringId": "1866446074436673536",
            "femaleVariant": "Ah, fuck...!"
          },
          {
            "stringId": "1866448933257502720",
            "femaleVariant": "Ugh, the hell's that?"
          },
          {
            "stringId": "1866470373734244352",
            "femaleVariant": "Well, sooner or later, Mikoshi's where we're headed."
          },
          {
            "stringId": "1866471602900197376",
            "femaleVariant": "Already got my plan, thanks. And I'm gonna stick to it."
          },
          {
            "stringId": "1866473099176206336",
            "femaleVariant": "Tellin' ya, sooner or later, Mikoshi's where we're headed."
          },
          {
            "stringId": "1916037551582031872",
            "femaleVariant": "Asked you – what the hell do you want?"
          },
          {
            "stringId": "1916043830555783168",
            "femaleVariant": "Fucked in the head worse than me."
          },
          {
            "stringId": "1916053337449115648",
            "femaleVariant": "For some ideal? Or to square a grudge?"
          },
          {
            "stringId": "1916054396678647808",
            "femaleVariant": "But why? Fightin' for some dated ideal? Pursuin' a personal vendetta?"
          },
          {
            "stringId": "1916065586494517248",
            "femaleVariant": "Ravings of a lunatic."
          },
          {
            "stringId": "1916082396644192260",
            "femaleVariant": "Following."
          },
          {
            "stringId": "1916083048120266752",
            "femaleVariant": "Don't care."
          },
          {
            "stringId": "1916087250544439296",
            "femaleVariant": "Yep, saw what happened to you."
          },
          {
            "stringId": "1947684874621575168",
            "femaleVariant": "Agh, fuck!"
          },
          {
            "stringId": "1947692891563909124",
            "femaleVariant": "[Sit] Dunno."
          },
          {
            "stringId": "1947692955602542596",
            "femaleVariant": "[Sit]"
          },
          {
            "stringId": "1947693299686465536",
            "femaleVariant": "Aghh... Not sure..."
          },
          {
            "stringId": "1947693657427042304",
            "femaleVariant": "Ugh... No idea..."
          },
          {
            "stringId": "1947745534776729600",
            "femaleVariant": "Hell's wrong with you?"
          },
          {
            "stringId": "1947746372597342208",
            "femaleVariant": "Still wanna find Parker, shape you're in?"
          },
          {
            "stringId": "1947746827830321152",
            "femaleVariant": "Really think you'll find Hellman or Parker, condition you're in?"
          },
          {
            "stringId": "1947750224914571264",
            "femaleVariant": "To croak in the shadow of some megablock?"
          },
          {
            "stringId": "1947750332792070144",
            "femaleVariant": "To sell yourself to the 'Sakas? They'll end you, plain as that."
          },
          {
            "stringId": "1947750376664489984",
            "femaleVariant": "To croak outside some flea-ridden motel?"
          },
          {
            "stringId": "1947809595019255808",
            "femaleVariant": "You don't need to know. Here to get me from point A to point B."
          },
          {
            "stringId": "1947834468986806272",
            "femaleVariant": "This time bomb's named Alt Cunningham."
          },
          {
            "stringId": "1947836553992101888",
            "femaleVariant": "Not yet. But you will once we find what we need."
          },
          {
            "stringId": "1947846786500026368",
            "femaleVariant": "Enough to know this is bullshit."
          },
          {
            "stringId": "1947889810999369728",
            "femaleVariant": "For now, we got no time to lose, need to get inside Mikoshi."
          },
          {
            "stringId": "1947895809793613824",
            "femaleVariant": "You fuckin' asshole…"
          },
          {
            "stringId": "1947896493213507584",
            "femaleVariant": "But as should be obvious, I've decided to help you. Need to find somethin' first – seven letters, starts with an M…"
          },
          {
            "stringId": "1947903429099151360",
            "femaleVariant": "[Stand] OK, talked enough."
          },
          {
            "stringId": "1947903684028948480",
            "femaleVariant": "Feelin' a bit better now, so scram. Got somethin' important needs doin'."
          },
          {
            "stringId": "1947904623888588800",
            "femaleVariant": "One last thing. Alt Cunningham – she's the ace up my sleeve."
          },
          {
            "stringId": "1947906161000341504",
            "femaleVariant": "Oh, fuck off. Tired of hearing your voice.",
            "maleVariant": "Oh, fuck off. I'm tired of hearing your voice."
          },
          {
            "stringId": "1947906559358558208",
            "femaleVariant": "Don't blame ya, but you'll hear me yet. And don't get killed in the meantime, will ya?"
          },
          {
            "stringId": "1954588837820260352",
            "femaleVariant": "I'm s'posed to know who that is?"
          },
          {
            "stringId": "1956200325843058688",
            "femaleVariant": "Gonna decomish before we learn how to rip the chip out."
          },
          {
            "stringId": "1956363546109476864",
            "femaleVariant": "That's what I need you for."
          },
          {
            "stringId": "1957365879334789120",
            "femaleVariant": "No, no, dammit!"
          },
          {
            "stringId": "1957367139656032256",
            "femaleVariant": "What the fuck you gawkin' at?"
          },
          {
            "stringId": "1957368517937881088",
            "femaleVariant": "Whaddaya want?!"
          },
          {
            "stringId": "1957368653296459776",
            "femaleVariant": "Fuck off, not your biz."
          },
          {
            "stringId": "1957368975066685440",
            "femaleVariant": "Man, if I only had some heat in my hand…"
          },
          {
            "stringId": "1957369053047185408",
            "femaleVariant": "The fuck--?!"
          },
          {
            "stringId": "1973200741042171908",
            "femaleVariant": "[Stand]"
          },
          {
            "stringId": "2054991439189454852",
            "femaleVariant": "What do you want from me?"
          }
        ]
      }



