{















        "entries": [
          {
            "stringId": "2167915868692697088",
            "femaleVariant": "Don't get it, choom. Been thinkin' and thinkin', but I just don't get it."
          },
          {
            "stringId": "2182248835446001664",
            "femaleVariant": "Get what?"
          },
          {
            "stringId": "2182248903511166976",
            "femaleVariant": "All that food in the dumpsters. Good food! If they don't want it, why don't they just give it to us?"
          },
          {
            "stringId": "2182249951214751744",
            "femaleVariant": "'Cause they don't even like to think about us. Simple as that."
          }
        ]
      }



