{















        "entries": [
          {
            "stringId": "2160375145841074176",
            "femaleVariant": "Poverty might well be our lot, guv'nor, but order must be maintained."
          },
          {
            "stringId": "2179780880398389248",
            "femaleVariant": "Without order, man's but like a beast, ya feel me?"
          },
          {
            "stringId": "2179782300136738816",
            "femaleVariant": "But Morty, I'm just... just... fuckin' hungry."
          },
          {
            "stringId": "2179782425227661312",
            "femaleVariant": "Hierarchy's inviolable, choom! Everyone's gotta know their place. Best bits go to Cataract Candy, I come second, you bring up the rear."
          },
          {
            "stringId": "2179783210686582784",
            "femaleVariant": "That ain't fair. Dude gives you the scop for free. We should all get the same."
          },
          {
            "stringId": "2179788644071870464",
            "femaleVariant": "Hey, if this arrangement ain't to your likin', you don't need to hang with us. Go on, see how you manage alone a while."
          },
          {
            "stringId": "2179788770521747456",
            "femaleVariant": "All right, don't need to hear that shit."
          }
        ]
      }



